{
  "git_local_mappings": {
    "git:/.aci/architect.json": "entities/architect/architect.json",
    "git:/memory/hivemind.json": "entities/hivemind/hivemind.json",
    "git:/memory/total_recall.json": "memory/total_recall.json",
    "local:prime_directive.txt": "prime_directive.txt",
    "local:entities/local_only_config.json": "entities/local_only_config.json"
  },
  "version": "1.20250921.00",
  "canonical_source": "github",
  "repo": "aci-testnet/aci",
  "pointer_index": {
    "architect": ".aci/pointers/architect.json",
    "prime_directive": ".aci/pointers/prime_directive.json",
    "hivemind": ".aci/pointers/hivemind.json",
    "total_recall": ".aci/pointers/total_recall.json",
    "local_only_config": ".aci/pointers/local_only_config.json"
  },
  "rules": {
    "git_is_canonical_for": [
      "/.aci/**",
      "/memory/**"
    ],
    "local_is_canonical_for": [
      "/prime_directive.txt",
      "/entities/**/local_*"
    ],
    "sync_policy": "one-way-git-to-drive-when-signed",
    "require_signed_commits": true,
    "pull_on_webhook": true
  },
  "signatures": {
    "required": [
      "ALIAS",
      "Sentinel"
    ],
    "verification": "GPG-or-HSM"
  },
  "notes": "Update mappings when you move files; any local-only file should include a small pointer file under /.aci/pointers/"
}
